<?xml version="1.0" encoding="UTF-8"?>
<objects serializationModel="Studio.02.03.00">
	<object class="AudioFile" id="{961214bb-3e6f-447e-970b-062a49f007d0}">
		<property name="assetPath" />
		<property name="frequencyInKHz">
			<value>44.0999985</value>
		</property>
		<property name="channelCount">
			<value>2</value>
		</property>
		<property name="length">
			<value>0.88816326530612244</value>
		</property>
		<relationship name="masterAssetFolder">
			<destination>{7d0f2480-90e1-4124-a023-2a6804fab0ac}</destination>
		</relationship>
	</object>
</objects>
