<?xml version="1.0" encoding="UTF-8"?>
<objects serializationModel="Studio.02.03.00">
	<object class="AudioFile" id="{6603f96d-7520-4409-8a6a-1b6397db7d8b}">
		<property name="assetPath">
			<value>tick_01.wav</value>
		</property>
		<property name="frequencyInKHz">
			<value>44.0999985</value>
		</property>
		<property name="channelCount">
			<value>2</value>
		</property>
		<property name="length">
			<value>0.8125170068027211</value>
		</property>
		<relationship name="masterAssetFolder">
			<destination>{7d0f2480-90e1-4124-a023-2a6804fab0ac}</destination>
		</relationship>
	</object>
</objects>
